ydb_function_driver/__init__.py
ydb_function_driver-0.4.dist-info/LICENSE
ydb_function_driver-0.4.dist-info/METADATA
ydb_function_driver-0.4.dist-info/WHEEL
ydb_function_driver-0.4.dist-info/top_level.txt
ydb_function_driver-0.4.dist-info/RECORD
