Metadata-Version: 2.1
Name: ydb-function-driver
Version: 0.4
Summary: Yandex database (ydb) driver for cloud function.
Home-page: https://github.com/yababay/ydb-function-driver
Download-URL: https://github.com/yababay/ydb-function-driver/archive/v_01.tar.gz
Author: Михаил Беляков (Michael Belyakov)
Author-email: bigbelk@live.ru
License: MIT
Keywords: ydb,cloud function,database driver
Platform: UNKNOWN
Classifier: Development Status :: 3 - Alpha
Classifier: Intended Audience :: Developers
Classifier: Topic :: Software Development :: Build Tools
Classifier: License :: OSI Approved :: MIT License
Classifier: Programming Language :: Python :: 3.9
License-File: LICENSE
Requires-Dist: ydb
